.gitignore
MANIFEST.in
README.rst
bootstrap.py
buildout.cfg
setup.cfg
setup.py
warmup.ini
docs/HISTORY.txt
docs/INSTALL.txt
docs/LICENSE.GPL
docs/LICENSE.txt
src/collective/__init__.py
src/collective.warmup.egg-info/PKG-INFO
src/collective.warmup.egg-info/SOURCES.txt
src/collective.warmup.egg-info/dependency_links.txt
src/collective.warmup.egg-info/entry_points.txt
src/collective.warmup.egg-info/namespace_packages.txt
src/collective.warmup.egg-info/not-zip-safe
src/collective.warmup.egg-info/requires.txt
src/collective.warmup.egg-info/top_level.txt
src/collective/warmup/__init__.py
src/collective/warmup/browser.py
src/collective/warmup/checker.py
src/collective/warmup/commands.py
src/collective/warmup/config.py
src/collective/warmup/configure.zcml
src/collective/warmup/event.py