Metadata-Version: 1.1
Name: collective.warmup
Version: 1.2
Summary: Collective Warmup
Home-page: http://svn.plone.org/svn/collective/
Author: Giorgio Borelli
Author-email: giorgio@giorgioborelli.it
License: GPL
Platform: UNKNOWN
Classifier: Programming Language :: Python
Classifier: Intended Audience :: System Administrators
Classifier: License :: OSI Approved :: GNU General Public License (GPL)
Classifier: Topic :: Internet
Classifier: Topic :: System :: Monitoring
Classifier: Topic :: Utilities
